geniverse/__init__.py
geniverse/modeling_utils.py
geniverse/models/__init__.py
geniverse/models/aphantasia/__init__.py
geniverse/models/aphantasia/modeling_aphantasia.py
geniverse/models/dalle_mini/__init__.py
geniverse/models/dalle_mini/modeling_dalle_mini.py
geniverse/models/glide/__init__.py
geniverse/models/glide/modeling_glide.py
geniverse/models/taming/__init__.py
geniverse/models/taming/modeling_taming.py
geniverse-0.1.10.dist-info/LICENSE
geniverse-0.1.10.dist-info/METADATA
geniverse-0.1.10.dist-info/WHEEL
geniverse-0.1.10.dist-info/top_level.txt
geniverse-0.1.10.dist-info/RECORD
