Metadata-Version: 2.1
Name: geniverse
Version: 0.1.10
Summary: Open-source library for guiding generative AI models.
Home-page: https://github.com/thegeniverse/geniverse
Author: Geniverse
Author-email: vipermu97@gmail.com
License: UNKNOWN
Project-URL: Docs, https://github.com/thegeniverse/geniverse/docs
Platform: UNKNOWN
Classifier: Programming Language :: Python :: 3
Classifier: License :: OSI Approved :: MIT License
Classifier: Operating System :: OS Independent
Requires-Python: >=3.6
License-File: LICENSE
Requires-Dist: geniverse-hub (>=0.0.5)
